opthub_client/__init__.py
opthub_client/api.py
opthub_client/context/__init__.py
opthub_client/context/cipher_suite.py
opthub_client/context/credentials.py
opthub_client/context/match_selection.py
opthub_client/context/utils.py
opthub_client/context/version.py
opthub_client/controllers/__init__.py
opthub_client/controllers/create.py
opthub_client/controllers/create_api_key.py
opthub_client/controllers/download.py
opthub_client/controllers/help.py
opthub_client/controllers/login.py
opthub_client/controllers/logout.py
opthub_client/controllers/select.py
opthub_client/controllers/show.py
opthub_client/controllers/show_trial.py
opthub_client/controllers/show_trials.py
opthub_client/controllers/submit.py
opthub_client/controllers/utils.py
opthub_client/errors/__init__.py
opthub_client/errors/authentication_error.py
opthub_client/errors/cache_io_error.py
opthub_client/errors/fetch_error.py
opthub_client/errors/graphql_error.py
opthub_client/errors/mutation_error.py
opthub_client/errors/query_error.py
opthub_client/errors/user_input_error.py
opthub_client/graphql/__init__.py
opthub_client/graphql/client.py
opthub_client/models/__init__.py
opthub_client/models/api_key.py
opthub_client/models/competition.py
opthub_client/models/match.py
opthub_client/models/remote_message.py
opthub_client/models/solution.py
opthub_client/models/trial.py
opthub_client/opt.py
opthub_client/validators/__init__.py
opthub_client/validators/solution.py
opthub_client/view/__init__.py
opthub_client/view/display_trials.py
opthub_client-0.8.1.dist-info/METADATA
opthub_client-0.8.1.dist-info/WHEEL
opthub_client-0.8.1.dist-info/entry_points.txt
opthub_client-0.8.1.dist-info/RECORD
