Metadata-Version: 2.1
Name: opthub_client
Version: 0.8.1
Summary: Library for Opthub CLI tools.
Home-page: https://github.com/opthub-org/opthub-client
License: MIT
Keywords: opthub,cli
Author: Opthub Inc.
Author-email: dev@opthub.ai
Requires-Python: >=3.10,<4.0
Classifier: License :: OSI Approved :: MIT License
Classifier: Programming Language :: Python :: 3
Classifier: Programming Language :: Python :: 3.10
Classifier: Programming Language :: Python :: 3.11
Classifier: Programming Language :: Python :: 3.12
Classifier: Programming Language :: Python :: 3.13
Requires-Dist: aiohttp (>=3.9.3,<4.0.0)
Requires-Dist: boto3 (>=1.34,<2.0)
Requires-Dist: click (>=8.1.7,<9.0.0)
Requires-Dist: cryptography (>=42.0.7,<43.0.0)
Requires-Dist: gql (>=3.5.0,<4.0.0)
Requires-Dist: inquirerpy (>=0.3.4,<0.4.0)
Requires-Dist: jwcrypto (>=1.5.6,<2.0.0)
Requires-Dist: numpy (>=2.1.0,<3.0.0)
Requires-Dist: opthub-api-client (>=0.3.0,<0.4)
Requires-Dist: prompt-toolkit (>=3.0.43,<4.0.0)
Requires-Dist: pyjwt (>=2.8.0,<3.0.0)
Requires-Dist: requests (>=2.31.0,<3.0.0)
Project-URL: Documentation, https://github.com/opthub-org/opthub-client
Project-URL: Repository, https://github.com/opthub-org/opthub-client
